{
  "models": {
    "Customer": {
      "id": "public.Customer",
      "schemaName": "public",
      "tableName": "Customer",
      "fields": [
        {
          "id": "public.Customer.id",
          "name": "id",
          "columnName": "id",
          "type": "text",
          "isRequired": true,
          "kind": "scalar",
          "isList": false,
          "isGenerated": false,
          "sequence": false,
          "hasDefaultValue": false,
          "isId": true,
          "maxLength": null
        },
        {
          "id": "public.Customer.name",
          "name": "name",
          "columnName": "name",
          "type": "text",
          "isRequired": true,
          "kind": "scalar",
          "isList": false,
          "isGenerated": false,
          "sequence": false,
          "hasDefaultValue": false,
          "isId": false,
          "maxLength": null
        },
        {
          "id": "public.Customer.createdAt",
          "name": "createdAt",
          "columnName": "createdAt",
          "type": "timestamp",
          "isRequired": true,
          "kind": "scalar",
          "isList": false,
          "isGenerated": false,
          "sequence": false,
          "hasDefaultValue": true,
          "isId": false,
          "maxLength": null
        },
        {
          "id": "public.Customer.updatedAt",
          "name": "updatedAt",
          "columnName": "updatedAt",
          "type": "timestamp",
          "isRequired": false,
          "kind": "scalar",
          "isList": false,
          "isGenerated": false,
          "sequence": false,
          "hasDefaultValue": false,
          "isId": false,
          "maxLength": null
        },
        {
          "name": "Location",
          "type": "Location",
          "isRequired": false,
          "kind": "object",
          "relationName": "LocationToCustomer",
          "relationFromFields": [],
          "relationToFields": [],
          "isList": true,
          "isId": false,
          "isGenerated": false,
          "sequence": false,
          "hasDefaultValue": false
        }
      ],
      "uniqueConstraints": [
        {
          "name": "Customer_pkey",
          "fields": [
            "id"
          ],
          "nullNotDistinct": false
        },
        {
          "name": "Customer_name_key",
          "fields": [
            "name"
          ],
          "nullNotDistinct": false
        }
      ]
    },
    "Device": {
      "id": "public.Device",
      "schemaName": "public",
      "tableName": "Device",
      "fields": [
        {
          "id": "public.Device.id",
          "name": "id",
          "columnName": "id",
          "type": "text",
          "isRequired": true,
          "kind": "scalar",
          "isList": false,
          "isGenerated": false,
          "sequence": false,
          "hasDefaultValue": false,
          "isId": true,
          "maxLength": null
        },
        {
          "id": "public.Device.name",
          "name": "name",
          "columnName": "name",
          "type": "text",
          "isRequired": true,
          "kind": "scalar",
          "isList": false,
          "isGenerated": false,
          "sequence": false,
          "hasDefaultValue": false,
          "isId": false,
          "maxLength": null
        },
        {
          "id": "public.Device.mac",
          "name": "mac",
          "columnName": "mac",
          "type": "text",
          "isRequired": true,
          "kind": "scalar",
          "isList": false,
          "isGenerated": false,
          "sequence": false,
          "hasDefaultValue": false,
          "isId": false,
          "maxLength": null
        },
        {
          "id": "public.Device.ip",
          "name": "ip",
          "columnName": "ip",
          "type": "text",
          "isRequired": true,
          "kind": "scalar",
          "isList": false,
          "isGenerated": false,
          "sequence": false,
          "hasDefaultValue": false,
          "isId": false,
          "maxLength": null
        },
        {
          "id": "public.Device.pin",
          "name": "pin",
          "columnName": "pin",
          "type": "int4",
          "isRequired": true,
          "kind": "scalar",
          "isList": false,
          "isGenerated": false,
          "sequence": false,
          "hasDefaultValue": false,
          "isId": false,
          "maxLength": null
        },
        {
          "id": "public.Device.deviceTypeId",
          "name": "deviceTypeId",
          "columnName": "deviceTypeId",
          "type": "text",
          "isRequired": false,
          "kind": "scalar",
          "isList": false,
          "isGenerated": false,
          "sequence": false,
          "hasDefaultValue": false,
          "isId": false,
          "maxLength": null
        },
        {
          "id": "public.Device.groupId",
          "name": "groupId",
          "columnName": "groupId",
          "type": "text",
          "isRequired": false,
          "kind": "scalar",
          "isList": false,
          "isGenerated": false,
          "sequence": false,
          "hasDefaultValue": false,
          "isId": false,
          "maxLength": null
        },
        {
          "id": "public.Device.locationId",
          "name": "locationId",
          "columnName": "locationId",
          "type": "text",
          "isRequired": false,
          "kind": "scalar",
          "isList": false,
          "isGenerated": false,
          "sequence": false,
          "hasDefaultValue": false,
          "isId": false,
          "maxLength": null
        },
        {
          "id": "public.Device.createdAt",
          "name": "createdAt",
          "columnName": "createdAt",
          "type": "timestamp",
          "isRequired": true,
          "kind": "scalar",
          "isList": false,
          "isGenerated": false,
          "sequence": false,
          "hasDefaultValue": true,
          "isId": false,
          "maxLength": null
        },
        {
          "id": "public.Device.updatedAt",
          "name": "updatedAt",
          "columnName": "updatedAt",
          "type": "timestamp",
          "isRequired": false,
          "kind": "scalar",
          "isList": false,
          "isGenerated": false,
          "sequence": false,
          "hasDefaultValue": false,
          "isId": false,
          "maxLength": null
        },
        {
          "name": "DeviceType",
          "type": "DeviceType",
          "isRequired": false,
          "kind": "object",
          "relationName": "DeviceToDeviceType",
          "relationFromFields": [
            "deviceTypeId"
          ],
          "relationToFields": [
            "id"
          ],
          "isList": false,
          "isId": false,
          "isGenerated": false,
          "sequence": false,
          "hasDefaultValue": false
        },
        {
          "name": "Group",
          "type": "Group",
          "isRequired": false,
          "kind": "object",
          "relationName": "DeviceToGroup",
          "relationFromFields": [
            "groupId"
          ],
          "relationToFields": [
            "id"
          ],
          "isList": false,
          "isId": false,
          "isGenerated": false,
          "sequence": false,
          "hasDefaultValue": false
        },
        {
          "name": "Location",
          "type": "Location",
          "isRequired": false,
          "kind": "object",
          "relationName": "DeviceToLocation",
          "relationFromFields": [
            "locationId"
          ],
          "relationToFields": [
            "id"
          ],
          "isList": false,
          "isId": false,
          "isGenerated": false,
          "sequence": false,
          "hasDefaultValue": false
        }
      ],
      "uniqueConstraints": [
        {
          "name": "Device_pkey",
          "fields": [
            "id"
          ],
          "nullNotDistinct": false
        }
      ]
    },
    "DeviceType": {
      "id": "public.DeviceType",
      "schemaName": "public",
      "tableName": "DeviceType",
      "fields": [
        {
          "id": "public.DeviceType.id",
          "name": "id",
          "columnName": "id",
          "type": "text",
          "isRequired": true,
          "kind": "scalar",
          "isList": false,
          "isGenerated": false,
          "sequence": false,
          "hasDefaultValue": false,
          "isId": true,
          "maxLength": null
        },
        {
          "id": "public.DeviceType.name",
          "name": "name",
          "columnName": "name",
          "type": "text",
          "isRequired": true,
          "kind": "scalar",
          "isList": false,
          "isGenerated": false,
          "sequence": false,
          "hasDefaultValue": false,
          "isId": false,
          "maxLength": null
        },
        {
          "id": "public.DeviceType.createdAt",
          "name": "createdAt",
          "columnName": "createdAt",
          "type": "timestamp",
          "isRequired": true,
          "kind": "scalar",
          "isList": false,
          "isGenerated": false,
          "sequence": false,
          "hasDefaultValue": true,
          "isId": false,
          "maxLength": null
        },
        {
          "id": "public.DeviceType.updatedAt",
          "name": "updatedAt",
          "columnName": "updatedAt",
          "type": "timestamp",
          "isRequired": false,
          "kind": "scalar",
          "isList": false,
          "isGenerated": false,
          "sequence": false,
          "hasDefaultValue": false,
          "isId": false,
          "maxLength": null
        },
        {
          "name": "Device",
          "type": "Device",
          "isRequired": false,
          "kind": "object",
          "relationName": "DeviceToDeviceType",
          "relationFromFields": [],
          "relationToFields": [],
          "isList": true,
          "isId": false,
          "isGenerated": false,
          "sequence": false,
          "hasDefaultValue": false
        }
      ],
      "uniqueConstraints": [
        {
          "name": "DeviceType_pkey",
          "fields": [
            "id"
          ],
          "nullNotDistinct": false
        },
        {
          "name": "DeviceType_name_key",
          "fields": [
            "name"
          ],
          "nullNotDistinct": false
        }
      ]
    },
    "Group": {
      "id": "public.Group",
      "schemaName": "public",
      "tableName": "Group",
      "fields": [
        {
          "id": "public.Group.id",
          "name": "id",
          "columnName": "id",
          "type": "text",
          "isRequired": true,
          "kind": "scalar",
          "isList": false,
          "isGenerated": false,
          "sequence": false,
          "hasDefaultValue": false,
          "isId": true,
          "maxLength": null
        },
        {
          "id": "public.Group.name",
          "name": "name",
          "columnName": "name",
          "type": "text",
          "isRequired": true,
          "kind": "scalar",
          "isList": false,
          "isGenerated": false,
          "sequence": false,
          "hasDefaultValue": false,
          "isId": false,
          "maxLength": null
        },
        {
          "id": "public.Group.locationId",
          "name": "locationId",
          "columnName": "locationId",
          "type": "text",
          "isRequired": false,
          "kind": "scalar",
          "isList": false,
          "isGenerated": false,
          "sequence": false,
          "hasDefaultValue": false,
          "isId": false,
          "maxLength": null
        },
        {
          "id": "public.Group.createdAt",
          "name": "createdAt",
          "columnName": "createdAt",
          "type": "timestamp",
          "isRequired": true,
          "kind": "scalar",
          "isList": false,
          "isGenerated": false,
          "sequence": false,
          "hasDefaultValue": true,
          "isId": false,
          "maxLength": null
        },
        {
          "id": "public.Group.updatedAt",
          "name": "updatedAt",
          "columnName": "updatedAt",
          "type": "timestamp",
          "isRequired": false,
          "kind": "scalar",
          "isList": false,
          "isGenerated": false,
          "sequence": false,
          "hasDefaultValue": false,
          "isId": false,
          "maxLength": null
        },
        {
          "name": "Location",
          "type": "Location",
          "isRequired": false,
          "kind": "object",
          "relationName": "GroupToLocation",
          "relationFromFields": [
            "locationId"
          ],
          "relationToFields": [
            "id"
          ],
          "isList": false,
          "isId": false,
          "isGenerated": false,
          "sequence": false,
          "hasDefaultValue": false
        },
        {
          "name": "Device",
          "type": "Device",
          "isRequired": false,
          "kind": "object",
          "relationName": "DeviceToGroup",
          "relationFromFields": [],
          "relationToFields": [],
          "isList": true,
          "isId": false,
          "isGenerated": false,
          "sequence": false,
          "hasDefaultValue": false
        }
      ],
      "uniqueConstraints": [
        {
          "name": "Group_pkey",
          "fields": [
            "id"
          ],
          "nullNotDistinct": false
        }
      ]
    },
    "Location": {
      "id": "public.Location",
      "schemaName": "public",
      "tableName": "Location",
      "fields": [
        {
          "id": "public.Location.id",
          "name": "id",
          "columnName": "id",
          "type": "text",
          "isRequired": true,
          "kind": "scalar",
          "isList": false,
          "isGenerated": false,
          "sequence": false,
          "hasDefaultValue": false,
          "isId": true,
          "maxLength": null
        },
        {
          "id": "public.Location.address",
          "name": "address",
          "columnName": "address",
          "type": "text",
          "isRequired": true,
          "kind": "scalar",
          "isList": false,
          "isGenerated": false,
          "sequence": false,
          "hasDefaultValue": false,
          "isId": false,
          "maxLength": null
        },
        {
          "id": "public.Location.customerId",
          "name": "customerId",
          "columnName": "customerId",
          "type": "text",
          "isRequired": false,
          "kind": "scalar",
          "isList": false,
          "isGenerated": false,
          "sequence": false,
          "hasDefaultValue": false,
          "isId": false,
          "maxLength": null
        },
        {
          "id": "public.Location.createdAt",
          "name": "createdAt",
          "columnName": "createdAt",
          "type": "timestamp",
          "isRequired": true,
          "kind": "scalar",
          "isList": false,
          "isGenerated": false,
          "sequence": false,
          "hasDefaultValue": true,
          "isId": false,
          "maxLength": null
        },
        {
          "id": "public.Location.updatedAt",
          "name": "updatedAt",
          "columnName": "updatedAt",
          "type": "timestamp",
          "isRequired": false,
          "kind": "scalar",
          "isList": false,
          "isGenerated": false,
          "sequence": false,
          "hasDefaultValue": false,
          "isId": false,
          "maxLength": null
        },
        {
          "name": "Customer",
          "type": "Customer",
          "isRequired": false,
          "kind": "object",
          "relationName": "LocationToCustomer",
          "relationFromFields": [
            "customerId"
          ],
          "relationToFields": [
            "id"
          ],
          "isList": false,
          "isId": false,
          "isGenerated": false,
          "sequence": false,
          "hasDefaultValue": false
        },
        {
          "name": "Device",
          "type": "Device",
          "isRequired": false,
          "kind": "object",
          "relationName": "DeviceToLocation",
          "relationFromFields": [],
          "relationToFields": [],
          "isList": true,
          "isId": false,
          "isGenerated": false,
          "sequence": false,
          "hasDefaultValue": false
        },
        {
          "name": "Group",
          "type": "Group",
          "isRequired": false,
          "kind": "object",
          "relationName": "GroupToLocation",
          "relationFromFields": [],
          "relationToFields": [],
          "isList": true,
          "isId": false,
          "isGenerated": false,
          "sequence": false,
          "hasDefaultValue": false
        }
      ],
      "uniqueConstraints": [
        {
          "name": "Location_pkey",
          "fields": [
            "id"
          ],
          "nullNotDistinct": false
        }
      ]
    },
    "Session": {
      "id": "public.Session",
      "schemaName": "public",
      "tableName": "Session",
      "fields": [
        {
          "id": "public.Session.id",
          "name": "id",
          "columnName": "id",
          "type": "text",
          "isRequired": true,
          "kind": "scalar",
          "isList": false,
          "isGenerated": false,
          "sequence": false,
          "hasDefaultValue": false,
          "isId": true,
          "maxLength": null
        },
        {
          "id": "public.Session.userId",
          "name": "userId",
          "columnName": "userId",
          "type": "text",
          "isRequired": true,
          "kind": "scalar",
          "isList": false,
          "isGenerated": false,
          "sequence": false,
          "hasDefaultValue": false,
          "isId": false,
          "maxLength": null
        },
        {
          "id": "public.Session.expiresAt",
          "name": "expiresAt",
          "columnName": "expiresAt",
          "type": "timestamp",
          "isRequired": true,
          "kind": "scalar",
          "isList": false,
          "isGenerated": false,
          "sequence": false,
          "hasDefaultValue": false,
          "isId": false,
          "maxLength": null
        },
        {
          "name": "User",
          "type": "User",
          "isRequired": true,
          "kind": "object",
          "relationName": "SessionToUser",
          "relationFromFields": [
            "userId"
          ],
          "relationToFields": [
            "id"
          ],
          "isList": false,
          "isId": false,
          "isGenerated": false,
          "sequence": false,
          "hasDefaultValue": false
        }
      ],
      "uniqueConstraints": [
        {
          "name": "Session_pkey",
          "fields": [
            "id"
          ],
          "nullNotDistinct": false
        }
      ]
    },
    "User": {
      "id": "public.User",
      "schemaName": "public",
      "tableName": "User",
      "fields": [
        {
          "id": "public.User.id",
          "name": "id",
          "columnName": "id",
          "type": "text",
          "isRequired": true,
          "kind": "scalar",
          "isList": false,
          "isGenerated": false,
          "sequence": false,
          "hasDefaultValue": false,
          "isId": true,
          "maxLength": null
        },
        {
          "id": "public.User.email",
          "name": "email",
          "columnName": "email",
          "type": "text",
          "isRequired": true,
          "kind": "scalar",
          "isList": false,
          "isGenerated": false,
          "sequence": false,
          "hasDefaultValue": false,
          "isId": false,
          "maxLength": null
        },
        {
          "id": "public.User.hashedPassword",
          "name": "hashedPassword",
          "columnName": "hashedPassword",
          "type": "text",
          "isRequired": true,
          "kind": "scalar",
          "isList": false,
          "isGenerated": false,
          "sequence": false,
          "hasDefaultValue": false,
          "isId": false,
          "maxLength": null
        },
        {
          "id": "public.User.createdAt",
          "name": "createdAt",
          "columnName": "createdAt",
          "type": "timestamp",
          "isRequired": true,
          "kind": "scalar",
          "isList": false,
          "isGenerated": false,
          "sequence": false,
          "hasDefaultValue": true,
          "isId": false,
          "maxLength": null
        },
        {
          "id": "public.User.updatedAt",
          "name": "updatedAt",
          "columnName": "updatedAt",
          "type": "timestamp",
          "isRequired": false,
          "kind": "scalar",
          "isList": false,
          "isGenerated": false,
          "sequence": false,
          "hasDefaultValue": false,
          "isId": false,
          "maxLength": null
        },
        {
          "name": "Session",
          "type": "Session",
          "isRequired": false,
          "kind": "object",
          "relationName": "SessionToUser",
          "relationFromFields": [],
          "relationToFields": [],
          "isList": true,
          "isId": false,
          "isGenerated": false,
          "sequence": false,
          "hasDefaultValue": false
        }
      ],
      "uniqueConstraints": [
        {
          "name": "User_pkey",
          "fields": [
            "id"
          ],
          "nullNotDistinct": false
        },
        {
          "name": "User_email_key",
          "fields": [
            "email"
          ],
          "nullNotDistinct": false
        }
      ]
    },
    "_prisma_migrations": {
      "id": "public._prisma_migrations",
      "schemaName": "public",
      "tableName": "_prisma_migrations",
      "fields": [
        {
          "id": "public._prisma_migrations.id",
          "name": "id",
          "columnName": "id",
          "type": "varchar",
          "isRequired": true,
          "kind": "scalar",
          "isList": false,
          "isGenerated": false,
          "sequence": false,
          "hasDefaultValue": false,
          "isId": true,
          "maxLength": 36
        },
        {
          "id": "public._prisma_migrations.checksum",
          "name": "checksum",
          "columnName": "checksum",
          "type": "varchar",
          "isRequired": true,
          "kind": "scalar",
          "isList": false,
          "isGenerated": false,
          "sequence": false,
          "hasDefaultValue": false,
          "isId": false,
          "maxLength": 64
        },
        {
          "id": "public._prisma_migrations.finished_at",
          "name": "finished_at",
          "columnName": "finished_at",
          "type": "timestamptz",
          "isRequired": false,
          "kind": "scalar",
          "isList": false,
          "isGenerated": false,
          "sequence": false,
          "hasDefaultValue": false,
          "isId": false,
          "maxLength": null
        },
        {
          "id": "public._prisma_migrations.migration_name",
          "name": "migration_name",
          "columnName": "migration_name",
          "type": "varchar",
          "isRequired": true,
          "kind": "scalar",
          "isList": false,
          "isGenerated": false,
          "sequence": false,
          "hasDefaultValue": false,
          "isId": false,
          "maxLength": 255
        },
        {
          "id": "public._prisma_migrations.logs",
          "name": "logs",
          "columnName": "logs",
          "type": "text",
          "isRequired": false,
          "kind": "scalar",
          "isList": false,
          "isGenerated": false,
          "sequence": false,
          "hasDefaultValue": false,
          "isId": false,
          "maxLength": null
        },
        {
          "id": "public._prisma_migrations.rolled_back_at",
          "name": "rolled_back_at",
          "columnName": "rolled_back_at",
          "type": "timestamptz",
          "isRequired": false,
          "kind": "scalar",
          "isList": false,
          "isGenerated": false,
          "sequence": false,
          "hasDefaultValue": false,
          "isId": false,
          "maxLength": null
        },
        {
          "id": "public._prisma_migrations.started_at",
          "name": "started_at",
          "columnName": "started_at",
          "type": "timestamptz",
          "isRequired": true,
          "kind": "scalar",
          "isList": false,
          "isGenerated": false,
          "sequence": false,
          "hasDefaultValue": true,
          "isId": false,
          "maxLength": null
        },
        {
          "id": "public._prisma_migrations.applied_steps_count",
          "name": "applied_steps_count",
          "columnName": "applied_steps_count",
          "type": "int4",
          "isRequired": true,
          "kind": "scalar",
          "isList": false,
          "isGenerated": false,
          "sequence": false,
          "hasDefaultValue": true,
          "isId": false,
          "maxLength": null
        }
      ],
      "uniqueConstraints": [
        {
          "name": "_prisma_migrations_pkey",
          "fields": [
            "id"
          ],
          "nullNotDistinct": false
        }
      ]
    }
  },
  "enums": {}
}